vearch/DataType.py
vearch/__init__.py
vearch/_swigvearch.cpython-37m-x86_64-linux-gnu.so
vearch/swigvearch.py
vearch/gamma_api/Attribute.py
vearch/gamma_api/BatchResult.py
vearch/gamma_api/CacheInfo.py
vearch/gamma_api/Config.py
vearch/gamma_api/Doc.py
vearch/gamma_api/EngineStatus.py
vearch/gamma_api/Field.py
vearch/gamma_api/FieldInfo.py
vearch/gamma_api/RangeFilter.py
vearch/gamma_api/Request.py
vearch/gamma_api/Response.py
vearch/gamma_api/ResultItem.py
vearch/gamma_api/SearchResult.py
vearch/gamma_api/SearchResultCode.py
vearch/gamma_api/Table.py
vearch/gamma_api/TermFilter.py
vearch/gamma_api/VectorInfo.py
vearch/gamma_api/VectorQuery.py
vearch/gamma_api/__init__.py
vearch-3.3.2.dist-info/LICENSE
vearch-3.3.2.dist-info/METADATA
vearch-3.3.2.dist-info/WHEEL
vearch-3.3.2.dist-info/top_level.txt
vearch-3.3.2.dist-info/RECORD
vearch.libs/libfaiss_avx2-a87f0f21.so
vearch.libs/libgfortran-91cc3cb1.so.3.0.0
vearch.libs/libopenblas-r0-f650aae0.3.3.so
vearch.libs/libquadmath-96973f99.so.0.0.0
vearch.libs/libcrypto-d3570994.so.1.0.2k
vearch.libs/libgomp-a34b3233.so.1.0.0
vearch.libs/libtbb-97796354.so.2
vearch.libs/libgamma-870f561b.so
vearch.libs/librocksdb-635c2631.so.6.6.4
vearch.libs/libzstd-8d126cbb.so.1.5.5
vearch.libs/libzfp-ba949209.so.0.5.5
