Metadata-Version: 2.1
Name: vearch
Version: 3.3.2
Summary: A library for efficient similarity search and storage of deep learning vectors.
Home-page: https://github.com/vearch/vearch
Author: vearch author
Author-email: vearch-maintainers@groups.io
License: Apache License, Version 2.0
Keywords: real time index,vector nearest neighbors
License-File: LICENSE
Requires-Dist: numpy (>=1.16.0)
Requires-Dist: flatbuffers (==1.12.0)
